CHANGES
LICENSE
MANIFEST.in
README.rst
internal.proto
setup.cfg
setup.py
imposm/900913.sql
imposm/__init__.py
imposm/app.py
imposm/base.py
imposm/config.py
imposm/dbimporter.py
imposm/defaultmapping.py
imposm/geom.py
imposm/mapping.py
imposm/merge.py
imposm/multipolygon.py
imposm/psqldb.py
imposm/reader.py
imposm/version.py
imposm/writer.py
imposm.egg-info/PKG-INFO
imposm.egg-info/SOURCES.txt
imposm.egg-info/dependency_links.txt
imposm.egg-info/entry_points.txt
imposm.egg-info/namespace_packages.txt
imposm.egg-info/requires.txt
imposm.egg-info/top_level.txt
imposm/cache/__init__.py
imposm/cache/internal.cc
imposm/cache/osm.py
imposm/cache/tc.c
imposm/cache/tc.pyx
imposm/db/__init__.py
imposm/db/config.py
imposm/db/postgis.py
imposm/test/__init__.py
imposm/test/test_cache.py
imposm/test/test_dbimporter.py
imposm/test/test_field_types.py
imposm/test/test_imported.py
imposm/test/test_large_limit_to_geom.py
imposm/test/test_limit_to.py
imposm/test/test_multipolygon.py
imposm/test/test_tag_mapper.py
imposm/util/__init__.py
imposm/util/geom.py
imposm/util/lib.py
imposm/util/ogr.py