Metadata-Version: 1.1
Name: imposm
Version: 2.6.0
Summary: OpenStreetMap importer for PostGIS.
Home-page: http://imposm.org/
Author: Oliver Tonnhofer
Author-email: olt@omniscale.de
License: Apache Software License 2.0
Platform: UNKNOWN
Classifier: Development Status :: 4 - Beta
Classifier: License :: OSI Approved :: Apache Software License
Classifier: Operating System :: OS Independent
Classifier: Programming Language :: C
Classifier: Programming Language :: C++
Classifier: Programming Language :: Python :: 2.5
Classifier: Programming Language :: Python :: 2.6
Classifier: Programming Language :: Python :: 2.7
Classifier: Topic :: Scientific/Engineering :: GIS
